babysploit/__init__.py
babysploit/__main__.py
babysploit/blackeye.py
babysploit/cloudflarebypass.py
babysploit/configuration.py
babysploit/display.py
babysploit/dnslookup.py
babysploit/ftpbruteforce.py
babysploit/ftpv.py
babysploit/helper.py
babysploit/iplookup.py
babysploit/nmtool.py
babysploit/reverseshell.py
babysploit/searchsploit.py
babysploit/tutorial.py
babysploit/utils.py
babysploit/wpseku.py
babysploit-1.5.dist-info/LICENSE.md
babysploit-1.5.dist-info/METADATA
babysploit-1.5.dist-info/WHEEL
babysploit-1.5.dist-info/entry_points.txt
babysploit-1.5.dist-info/top_level.txt
babysploit-1.5.dist-info/zip-safe
babysploit-1.5.dist-info/RECORD
